Metadata-Version: 2.4
Name: ai-shell-command-generator
Version: 2.5.0
Summary: AI-powered shell command generator with dual provider support and safety features
Author-email: Tim Kitchens <your-email@example.com>
License-Expression: MIT
Project-URL: Homepage, https://github.com/codingthefuturewithai/ai-shell-command-generator
Project-URL: Repository, https://github.com/codingthefuturewithai/ai-shell-command-generator
Project-URL: Issues, https://github.com/codingthefuturewithai/ai-shell-command-generator/issues
Project-URL: Documentation, https://github.com/codingthefuturewithai/ai-shell-command-generator#readme
Keywords: ai,shell,command,generator,anthropic,ollama,claude,gpt-oss,cli
Classifier: Development Status :: 4 - Beta
Classifier: Intended Audience :: Developers
Classifier: Intended Audience :: System Administrators
Classifier: Topic :: Software Development :: Libraries :: Python Modules
Classifier: Topic :: System :: Shells
Classifier: Topic :: System :: System Shells
Classifier: Programming Language :: Python :: 3
Classifier: Programming Language :: Python :: 3.10
Classifier: Programming Language :: Python :: 3.11
Classifier: Programming Language :: Python :: 3.12
Classifier: Operating System :: OS Independent
Requires-Python: >=3.10
License-File: LICENSE
Requires-Dist: anthropic>=0.69.0
Requires-Dist: openai>=1.0.0
Requires-Dist: python-dotenv>=1.1.1
Requires-Dist: click>=8.3.0
Requires-Dist: pyperclip>=1.11.0
Requires-Dist: ollama>=0.6.0
Provides-Extra: dev
Requires-Dist: pytest>=7.0.0; extra == "dev"
Requires-Dist: pytest-cov>=4.0.0; extra == "dev"
Requires-Dist: black>=22.0.0; extra == "dev"
Requires-Dist: flake8>=4.0.0; extra == "dev"
Provides-Extra: test
Requires-Dist: pytest>=7.0.0; extra == "test"
Requires-Dist: pytest-cov>=4.0.0; extra == "test"
Dynamic: license-file
